bioflow/__init__.py
bioflow/main_configs.py
bioflow/configs_manager.py
bioflow/internal_configs.py
bioflow/cli.py
bioflow/analysis_pipeline_example.py
bioflow/molecular_network/__init__.py
bioflow/molecular_network/InteractomeInterface.py
bioflow/molecular_network/interactome_analysis.py
bioflow/bio_db_parsers/reactomeParser.py
bioflow/bio_db_parsers/geneOntologyParser.py
bioflow/bio_db_parsers/__init__.py
bioflow/bio_db_parsers/PhosphositeParser.py
bioflow/bio_db_parsers/uniprotParser.py
bioflow/bio_db_parsers/tfParsers.py
bioflow/bio_db_parsers/proteinRelParsers.py
bioflow/bio_db_parsers/ComplexPortalParser.py
bioflow/configs/sources.ini
bioflow/configs/options.ini
bioflow/configs/predictions.ini
bioflow/configs/servers.ini
bioflow/configs/online_dbs.ini
bioflow/pre_processing/__init__.py
bioflow/pre_processing/rna_counts_analysis.py
bioflow/algorithms_bank/__init__.py
bioflow/algorithms_bank/conduction_routines.py
bioflow/neo4j_db/__init__.py
bioflow/neo4j_db/cypher_drivers.py
bioflow/neo4j_db/GraphDeclarator.py
bioflow/neo4j_db/db_io_routines.py
bioflow/utils/log_behavior.py
bioflow/utils/__init__.py
bioflow/utils/remap_IDs.py
bioflow/utils/top_level.py
bioflow/utils/dataviz.py
bioflow/utils/io_routines.py
bioflow/utils/linalg_routines.py
bioflow/utils/gdfExportInterface.py
bioflow/utils/usage_ex-average_path_length.py
bioflow/utils/general_utils/high_level_os_io.py
bioflow/utils/general_utils/__init__.py
bioflow/utils/general_utils/internet_io.py
bioflow/utils/general_utils/dict_like_configs_parser.py
bioflow/utils/general_utils/useful_wrappers.py
bioflow/db_importers/__init__.py
bioflow/db_importers/phosphosite_importer.py
bioflow/db_importers/complex_importer.py
bioflow/db_importers/tf_importers.py
bioflow/db_importers/go_and_uniprot_importer.py
bioflow/db_importers/biogrid_importer.py
bioflow/db_importers/import_main.py
bioflow/db_importers/reactome_importer.py
bioflow/db_importers/hint_importer.py
BioFlow-0.2.3.dist-info/WHEEL
BioFlow-0.2.3.dist-info/DESCRIPTION.rst
BioFlow-0.2.3.dist-info/RECORD
BioFlow-0.2.3.dist-info/METADATA
BioFlow-0.2.3.dist-info/top_level.txt
BioFlow-0.2.3.dist-info/metadata.json
BioFlow-0.2.3.dist-info/entry_points.txt
