Metadata-Version: 2.0
Name: BioFlow
Version: 0.2.3
Summary: Information Flow Analysis in biological networks
Home-page: https://github.com/chiffa/BioFlow
Author: Andrei Kucharavy
Author-email: andrei.chiffa136@gmail.com
License: BSD
Keywords: network analysis,systems biology,interactome,computational biology
Platform: UNKNOWN
Classifier: Development Status :: 3 - Alpha
Classifier: Intended Audience :: Science/Research
Classifier: Intended Audience :: Healthcare Industry
Classifier: Intended Audience :: Developers
Classifier: Topic :: Scientific/Engineering :: Bio-Informatics
Classifier: Topic :: Scientific/Engineering :: Information Analysis
Classifier: Topic :: Scientific/Engineering :: Medical Science Apps.
Classifier: Topic :: Software Development :: Libraries :: Python Modules
Classifier: Operating System :: POSIX :: Linux
Classifier: License :: OSI Approved :: BSD License
Classifier: Programming Language :: Python :: 2.7
Classifier: Programming Language :: Python :: Implementation :: CPython
Requires-Dist: numpy (<2.0)
Requires-Dist: scipy (<1.0)
Requires-Dist: matplotlib (<2.0)
Requires-Dist: scikit-learn (<0.17)
Requires-Dist: cython (<0.23)
Requires-Dist: pymongo (<4.0)
Requires-Dist: requests (<3.0)
Requires-Dist: click (<6.0)
Requires-Dist: scikits.sparse (<0.3)
Requires-Dist: mock (<2.0)
Requires-Dist: requests-ftp (<0.4)
Requires-Dist: neo4j-driver (<2.0)
Provides-Extra: ci
Requires-Dist: coverage; extra == 'ci'
Requires-Dist: pylint; extra == 'ci'
Requires-Dist: coveralls; extra == 'ci'
Requires-Dist: pyflakes; extra == 'ci'
Requires-Dist: pep-8-naming; extra == 'ci'
Requires-Dist: maccabe; extra == 'ci'
Requires-Dist: flake-8; extra == 'ci'
Provides-Extra: dev
Provides-Extra: test
